spdiu/__init__.py
spdiu/cli.py
spdiu/collections/__init__.py
spdiu/collections/cheats.py
spdiu/collections/dev.py
spdiu/collections/display.py
spdiu/collections/get.py
spdiu/collections/slots.py
spdiu/config.py
spdiu/model.py
spdiu/program.py
spdiu/spdiu.py
spdiu/templates/spdiu.yaml
spdiu/templates/tasks.py
spdiu/util.py
spdiu-0.1.2.dist-info/licenses/LICENSES/AGPL-3.0-or-later.txt
spdiu-0.1.2.dist-info/licenses/LICENSES/CC0-1.0.txt
spdiu-0.1.2.dist-info/WHEEL
spdiu-0.1.2.dist-info/entry_points.txt
spdiu-0.1.2.dist-info/METADATA
spdiu-0.1.2.dist-info/RECORD
