Metadata-Version: 2.4
Name: spdiu
Version: 0.1.2
Summary: A collection of Invoke tasks that manage Shattered Pixel Dungeon game data.
Keywords: shattered-pixel-dungeon,remix,download,play,save,cheat,inspect
Author: Tasos Alvas
Author-email: Tasos Alvas <tasos.alvas@qwertyuiopia.com>
License-Expression: AGPL-3.0-or-later
License-File: LICENSES/AGPL-3.0-or-later.txt
License-File: LICENSES/CC0-1.0.txt
Classifier: Environment :: Console
Classifier: Development Status :: 3 - Alpha
Classifier: Intended Audience :: End Users/Desktop
Classifier: License :: OSI Approved :: GNU Affero General Public License v3 or later (AGPLv3+)
Classifier: Operating System :: OS Independent
Classifier: Programming Language :: Python :: 3
Classifier: Programming Language :: Python :: 3.11
Classifier: Topic :: Games/Entertainment
Classifier: Topic :: Games/Entertainment :: Role-Playing
Classifier: Topic :: Software Development :: Libraries :: Python Modules
Classifier: Topic :: Utilities
Requires-Dist: invoke>=2.2.1
Requires-Python: >=3.11
Project-URL: Github, https://github.com/tasosalvas/spdiu/
Project-URL: PyPi, https://pypi.org/project/spdiu/
